LICENSE.txt
MANIFEST.in
README.md
pyproject.toml
setup.cfg
setup.py
src/hueprint/__init__.py
src/hueprint/types.py
src/hueprint/utils.py
src/hueprint.egg-info/PKG-INFO
src/hueprint.egg-info/SOURCES.txt
src/hueprint.egg-info/dependency_links.txt
src/hueprint.egg-info/top_level.txt