Metadata-Version: 2.1
Name: hueprint
Version: 1.0.1
Summary: A simple package that enables coloured output in Python console applications.
Home-page: https://github.com/matheusvilano/hueprint.git
Author: Matheus Vilano
Author-email: 
License: MIT
Project-URL: Author Website, https://www.matheusvilano.com/
Project-URL: Git Repository, https://github.com/matheusvilano/hueprint
Keywords: colour color hue console output print terminal text style format effect ANSI escape sequence
Classifier: Development Status :: 5 - Production/Stable
Classifier: Intended Audience :: Developers
Classifier: License :: OSI Approved :: MIT License
Classifier: Operating System :: OS Independent
Classifier: Programming Language :: Python :: 3
Requires-Python: >=3.3
License-File: LICENSE.txt
